[{"model": "company.tasktype", "pk": 1, "fields": {"name": "Bug"}}, {"model": "company.tasktype", "pk": 2, "fields": {"name": "New feature"}}, {"model": "company.tasktype", "pk": 3, "fields": {"name": "Breaking change"}}, {"model": "company.tasktype", "pk": 4, "fields": {"name": "Refactoring"}}, {"model": "company.tasktype", "pk": 5, "fields": {"name": "QA"}}, {"model": "company.position", "pk": 1, "fields": {"name": "Developer"}}, {"model": "company.position", "pk": 2, "fields": {"name": "Project Manager"}}, {"model": "company.position", "pk": 3, "fields": {"name": "QA"}}, {"model": "company.position", "pk": 4, "fields": {"name": "Designer"}}, {"model": "company.position", "pk": 5, "fields": {"name": "DevOps"}}, {"model": "company.worker", "pk": 1, "fields": {"password": "pbkdf2_sha256$390000$9uE1cx9vMlwFV4KrcJmr6A$ziJPywhOxkP6E34NcVpTo9gDyoL04tynxKb+sFbdRtY=", "last_login": "2023-02-09T09:47:19.638Z", "is_superuser": true, "username": "admin", "first_name": "Pavlo", "last_name": "Starodub", "email": "admin@example.com", "is_staff": true, "is_active": true, "date_joined": "2023-01-30T06:58:51Z", "position": 5, "groups": [], "user_permissions": []}}, {"model": "company.worker", "pk": 2, "fields": {"password": "pbkdf2_sha256$390000$ffZIu6IAiJs5C401jqyqLS$LNx3PGqBy7ul2tKgfGBXaUw/zLQfBcIrfR2/tQxHpkc=", "last_login": "2023-02-09T07:00:12.893Z", "is_superuser": false, "username": "igorastar", "first_name": "Igor", "last_name": "Starodub", "email": "igora@gmail.com", "is_staff": false, "is_active": true, "date_joined": "2023-01-30T07:59:42Z", "position": 2, "groups": [], "user_permissions": []}}, {"model": "company.worker", "pk": 3, "fields": {"password": "pbkdf2_sha256$390000$VyFuOkuH9rsueX4KtLtTZm$H7yoNt+g8lvQhA8+QwmXT+98M6R8IpH93Xbt+0lzkdo=", "last_login": null, "is_superuser": false, "username": "Andrewstream", "first_name": "Andry", "last_name": "Starodub", "email": "andrew@gmail.com", "is_staff": false, "is_active": true, "date_joined": "2023-01-30T08:00:22Z", "position": 5, "groups": [], "user_permissions": []}}, {"model": "company.worker", "pk": 4, "fields": {"password": "pbkdf2_sha256$390000$e377dGsVlHBaU5m3P7b0pE$Wt7EoH/CYyVNs7wKUzraRaOr/2mz70itRHLolTsx7/0=", "last_login": null, "is_superuser": false, "username": "Kateblack", "first_name": "Kate", "last_name": "Sutula", "email": "catniedzwiecka@gmail.com", "is_staff": false, "is_active": true, "date_joined": "2023-01-30T08:01:24Z", "position": 1, "groups": [], "user_permissions": []}}, {"model": "company.worker", "pk": 5, "fields": {"password": "pbkdf2_sha256$390000$CgDvzKPFWSsoeLvtcOcWix$msnUOe9h3Grd9Ec8jdi0PHQQ1Ku5smiWBcY68n6LWZ0=", "last_login": null, "is_superuser": false, "username": "Nadyawhite", "first_name": "Nadya", "last_name": "Severinova", "email": "natalia.monika.niedzwiecka@gmail.com", "is_staff": false, "is_active": true, "date_joined": "2023-01-30T08:02:48Z", "position": 3, "groups": [], "user_permissions": []}}, {"model": "company.worker", "pk": 6, "fields": {"password": "pbkdf2_sha256$390000$sRQSD0LsFWssZQXpEn1HRJ$MVLjCFhaTVA3JqV+JKPhgG9qrSnH4q7OcxR8aLggL1k=", "last_login": null, "is_superuser": true, "username": "admin3", "first_name": "", "last_name": "", "email": "", "is_staff": true, "is_active": true, "date_joined": "2023-02-05T19:55:05.912Z", "position": null, "groups": [], "user_permissions": []}}, {"model": "company.worker", "pk": 8, "fields": {"password": "pbkdf2_sha256$390000$85UjNUAmdfql3Kb3jwLUUZ$TPHsWkaXDdzc4JBz4HuA4tQWlMsixiQv9o1UG9m7XeE=", "last_login": null, "is_superuser": false, "username": "greenred", "first_name": "Joanne", "last_name": "Shevchenko", "email": "", "is_staff": false, "is_active": true, "date_joined": "2023-02-07T08:08:57.456Z", "position": 1, "groups": [], "user_permissions": []}}, {"model": "company.worker", "pk": 9, "fields": {"password": "pbkdf2_sha256$390000$vwsX4QwcV4HTXsTgcoAQ51$ctH0SDKn+I1UP8ouVbIqL7kKyrdHvIgwcngxnIicP4U=", "last_login": null, "is_superuser": false, "username": "brownman", "first_name": "Taras", "last_name": "Thorne", "email": "", "is_staff": false, "is_active": true, "date_joined": "2023-02-07T11:32:17.342Z", "position": 4, "groups": [], "user_permissions": []}}, {"model": "company.task", "pk": 1, "fields": {"name": "Fix Dashboard for Vacancies", "description": "Fix Dashboard for Vacancies and another things", "deadline": "2023-01-30", "is_completed": false, "priority": "B", "task_type": 1, "assignees": [1]}}, {"model": "company.task", "pk": 2, "fields": {"name": "Add sign-in with Google button", "description": "Add sign-in with Google button.Very important information", "deadline": "2023-04-16", "is_completed": false, "priority": "C", "task_type": 4, "assignees": [1]}}, {"model": "company.task", "pk": 3, "fields": {"name": "Fix numbers", "description": "Fix bug with numbers", "deadline": "2023-05-09", "is_completed": false, "priority": "B", "task_type": 3, "assignees": [1]}}, {"model": "company.task", "pk": 10, "fields": {"name": "Fix code", "description": "You should debug and fix this code", "deadline": "2022-05-18", "is_completed": false, "priority": "C", "task_type": 4, "assignees": [1]}}]